torchfix/__init__.py
torchfix/__main__.py
torchfix/common.py
torchfix/deprecated_symbols.yaml
torchfix/torchfix.py
torchfix/visitors/__init__.py
torchfix/visitors/deprecated_symbols/__init__.py
torchfix/visitors/deprecated_symbols/chain_matmul.py
torchfix/visitors/deprecated_symbols/cholesky.py
torchfix/visitors/deprecated_symbols/qr.py
torchfix/visitors/deprecated_symbols/range.py
torchfix/visitors/internal/__init__.py
torchfix/visitors/misc/__init__.py
torchfix/visitors/nonpublic/__init__.py
torchfix/visitors/performance/__init__.py
torchfix/visitors/security/__init__.py
torchfix/visitors/vision/__init__.py
torchfix/visitors/vision/pretrained.py
torchfix/visitors/vision/singleton_import.py
torchfix/visitors/vision/to_tensor.py
TorchFix-0.7.0.dist-info/LICENSE
TorchFix-0.7.0.dist-info/METADATA
TorchFix-0.7.0.dist-info/WHEEL
TorchFix-0.7.0.dist-info/entry_points.txt
TorchFix-0.7.0.dist-info/top_level.txt
TorchFix-0.7.0.dist-info/RECORD
