Metadata-Version: 2.1
Name: TorchFix
Version: 0.7.0
Summary: TorchFix - a linter for PyTorch-using code with autofix support
License: BSD License
Project-URL: Repository, https://github.com/pytorch-labs/torchfix
Project-URL: Bug Tracker, https://github.com/pytorch-labs/torchfix/issues
Classifier: Development Status :: 4 - Beta
Classifier: Programming Language :: Python
Requires-Python: >=3.9
License-File: LICENSE
Requires-Dist: flake8 >=3.8.2
Requires-Dist: PyYAML
Requires-Dist: libcst <1.6.0,>=1.5.0
Provides-Extra: dev
Requires-Dist: flake8 ==6.0.0 ; extra == 'dev'
Requires-Dist: pytest ==7.2.0 ; extra == 'dev'
Requires-Dist: libcst ==1.5.0 ; extra == 'dev'
Requires-Dist: types-PyYAML ==6.0.7 ; extra == 'dev'
Requires-Dist: mypy ==1.7.0 ; extra == 'dev'
Requires-Dist: black ==24.4.0 ; extra == 'dev'
Requires-Dist: pre-commit ==3.7.0 ; extra == 'dev'
